main.py
crawler_byte-0.0.2.dist-info/licenses/LICENCE.md
crawlerbyte/__init__.py
crawlerbyte/crawler.py
crawler_byte-0.0.2.dist-info/METADATA
crawler_byte-0.0.2.dist-info/WHEEL
crawler_byte-0.0.2.dist-info/top_level.txt
crawler_byte-0.0.2.dist-info/RECORD
