Metadata-Version: 2.4
Name: crawler_byte
Version: 0.0.2
Summary: A python package that crawls a directory recursively and returns the file names and file stats as well as execute a custom function passed as an argument.
Author-email: Sixtus Onumajuru <jigga.e10@gmail.com>
License-Expression: MIT
Project-URL: Homepage, https://github.com/jiggabyte/crawler_byte
Project-URL: Issues, https://github.com/jiggabyte/crawler_byte/issues
Classifier: Programming Language :: Python :: 3
Classifier: Operating System :: OS Independent
Requires-Python: >=3.8
License-File: LICENCE.md
Dynamic: license-file
